dsi_toolkit/__init__.py
dsi_toolkit/dsi_toolkit.py
dsi_toolkit-1.0.7.dist-info/licenses/LICENSE
dsi_toolkit-1.0.7.dist-info/METADATA
dsi_toolkit-1.0.7.dist-info/WHEEL
dsi_toolkit-1.0.7.dist-info/top_level.txt
dsi_toolkit-1.0.7.dist-info/RECORD
