Metadata-Version: 2.4
Name: dsi-toolkit
Version: 1.0.7
Summary: The provided script 'dsi-toolkit' leverages a package designed for identifying polynomial models.
Home-page: https://github.com/jimjonessm/dsi_toolkit_examples/
Author: Márcio Falcão dos Santos Barroso
Author-email: Márcio Falcão dos Santos Barroso <barroso@ufsj.edu.br>, "Eduardo M. A. M. Mendes" <emmendes@ufmg.br>, Jim Jones da Silveira Marciano <jimjonessm@gmail.com>
License: Proprietary
Project-URL: Homepage, https://github.com/jimjonessm/dsi_toolkit_examples/
Classifier: Development Status :: 5 - Production/Stable
Classifier: Programming Language :: Python :: 3
Classifier: Programming Language :: Python :: 3.7
Classifier: Programming Language :: Python :: 3.8
Classifier: Programming Language :: Python :: 3.9
Classifier: Programming Language :: Python :: 3.10
Classifier: Operating System :: OS Independent
Classifier: Topic :: Software Development :: Libraries
Classifier: License :: Other/Proprietary License
Classifier: Intended Audience :: Developers
Requires-Python: >=3.7
License-File: LICENSE
Requires-Dist: numpy
Requires-Dist: matplotlib
Dynamic: author
Dynamic: home-page
Dynamic: license-file
Dynamic: requires-python
